iotcoreapi/__init__.py
iotcoreapi/exceptions.py
iotcoreapi/iotcoreapi.py
iotcoreapi/nan_treatment.py
iotcore_api-1.4.1.dist-info/METADATA
iotcore_api-1.4.1.dist-info/WHEEL
iotcore_api-1.4.1.dist-info/RECORD
