Metadata-Version: 2.1
Name: iotcore-api
Version: 1.4.1
Summary: IoT core connection methods and utilities in Python
Keywords: iotcoreapi,goaigua
Author: Ricardo Gomez-Aldaravi
Author-email: ricardo.gomez.aldaravi@idrica.com
Requires-Python: >=3.8,<4.0
Classifier: Programming Language :: Python :: 3
Classifier: Programming Language :: Python :: 3.8
Classifier: Programming Language :: Python :: 3.9
Classifier: Programming Language :: Python :: 3.10
Classifier: Programming Language :: Python :: 3.11
Classifier: Programming Language :: Python :: 3.12
Requires-Dist: pandas (>=2.0.1,<3.0.0)
Requires-Dist: requests (>=2.30.0,<3.0.0)
Requires-Dist: urllib3 (>=2.0.3,<3.0.0)
